{
	"configurations" : 
	[
		{
			"directories" : 
			[
				{
					"build" : ".",
					"jsonFile" : "directory-.-Debug-d0094a50bb2071803777.json",
					"minimumCMakeVersion" : 
					{
						"string" : "3.21"
					},
					"projectIndex" : 0,
					"source" : ".",
					"targetIndexes" : 
					[
						0
					]
				}
			],
			"name" : "Debug",
			"projects" : 
			[
				{
					"directoryIndexes" : 
					[
						0
					],
					"name" : "Heap",
					"targetIndexes" : 
					[
						0
					]
				}
			],
			"targets" : 
			[
				{
					"directoryIndex" : 0,
					"id" : "Heap::@6890427a1f51a3e7e1df",
					"jsonFile" : "target-Heap-Debug-ea5f40b11a33bc286269.json",
					"name" : "Heap",
					"projectIndex" : 0
				}
			]
		}
	],
	"kind" : "codemodel",
	"paths" : 
	{
		"build" : "D:/AN_2_sem1/AF/Tema2/Heap/cmake-build-debug",
		"source" : "D:/AN_2_sem1/AF/Tema2/Heap"
	},
	"version" : 
	{
		"major" : 2,
		"minor" : 3
	}
}
